Metadata-Version: 2.1
Name: sqlite-minutils
Version: 4.0.1
Summary: A fork of sqlite-utils with CLI etc removed
Home-page: https://github.com/AnswerDotAI/sqlite-minutils
Author: Jeremy Howard
Author-email: github@jhoward.fastmail.fm
License: Apache Software License 2.0
Keywords: nbdev jupyter notebook python
Classifier: Development Status :: 4 - Beta
Classifier: Intended Audience :: Developers
Classifier: Natural Language :: English
Classifier: Programming Language :: Python :: 3.8
Classifier: Programming Language :: Python :: 3.9
Classifier: Programming Language :: Python :: 3.10
Classifier: License :: OSI Approved :: Apache Software License
Requires-Python: >=3.8
License-File: LICENSE
Requires-Dist: fastcore
Provides-Extra: dev
